vsutillib/config.py
vsutillib/files/__init__.py
vsutillib/files/fileutil.py
vsutillib/files/classes/DisplayPath.py
vsutillib/files/classes/__init__.py
vsutillib/files/classes/configurationsettings.py
vsutillib/log/__init__.py
vsutillib/log/classes/__init__.py
vsutillib/log/classes/logrotatehandler.py
vsutillib/macos/__init__.py
vsutillib/macos/utils.py
vsutillib/media/__init__.py
vsutillib/media/mediautils.py
vsutillib/media/classes/__init__.py
vsutillib/media/classes/mediafileinfo.py
vsutillib/misc/__init__.py
vsutillib/misc/cipher.py
vsutillib/misc/decorators.py
vsutillib/misc/regexutils.py
vsutillib/misc/strFormatTimeDelta.py
vsutillib/misc/classes/XLate.py
vsutillib/misc/classes/__init__.py
vsutillib/mkv/__init__.py
vsutillib/mkv/mkvutils.py
vsutillib/mkv/classes/__init__.py
vsutillib/mkv/classes/mkvattachments.py
vsutillib/mkv/classes/mkvclassutil.py
vsutillib/mkv/classes/mkvcommand.py
vsutillib/mkv/classes/mkvcommandparser.py
vsutillib/mkv/classes/verifycommand.py
vsutillib/mkv/classes/verifystructure.py
vsutillib/network/__init__.py
vsutillib/network/network.py
vsutillib/network/classes/__init__.py
vsutillib/network/classes/urlrequest.py
vsutillib/process/__init__.py
vsutillib/process/utils.py
vsutillib/process/classes/__init__.py
vsutillib/process/classes/multiprocessing.py
vsutillib/process/classes/multithreading.py
vsutillib/process/classes/runcommand.py
vsutillib/pyqt/__init__.py
vsutillib/pyqt/messagebox.py
vsutillib/pyqt/qtUtils.py
vsutillib/pyqt/classes/QActionWidget.py
vsutillib/pyqt/classes/QComboLineEdit.py
vsutillib/pyqt/classes/QDarkPalette.py
vsutillib/pyqt/classes/QFileListWidget.py
vsutillib/pyqt/classes/QFormatLabel.py
vsutillib/pyqt/classes/QGenericThreads.py
vsutillib/pyqt/classes/QGroupSignal.py
vsutillib/pyqt/classes/QLineFrame.py
vsutillib/pyqt/classes/QMenuWidget.py
vsutillib/pyqt/classes/QOutputTextWidget.py
vsutillib/pyqt/classes/QProgressBar.py
vsutillib/pyqt/classes/QProgressIndicator.py
vsutillib/pyqt/classes/QPushButtonWidget.py
vsutillib-1.6.4.dist-info/AUTHORS
vsutillib-1.6.4.dist-info/LICENSE.txt
vsutillib-1.6.4.dist-info/METADATA
vsutillib-1.6.4.dist-info/WHEEL
vsutillib-1.6.4.dist-info/top_level.txt
vsutillib-1.6.4.dist-info/RECORD
