Metadata-Version: 2.1
Name: vsutillib
Version: 1.6.4
Summary: Library module with miscellaneous convenience functions and classes
Home-page: https://pypi.org/project/vsutillib/
Author: Efrain Vergara
Author-email: akai10tsuki@gmail.com
License: MIT
Project-URL: Source, https://pypi.org/project/vsutillib/#files
Keywords: mkv multimedia video audio configuration
Platform: UNKNOWN
Classifier: Development Status :: 5 - Production/Stable
Classifier: Environment :: Console
Classifier: Environment :: MacOS X
Classifier: Environment :: Win32 (MS Windows)
Classifier: Environment :: X11 Applications :: Qt
Classifier: Intended Audience :: Developers
Classifier: Topic :: Multimedia :: Video
Classifier: Topic :: Software Development :: Libraries
Classifier: License :: OSI Approved :: MIT License
Classifier: Operating System :: MacOS :: MacOS X
Classifier: Operating System :: Microsoft :: Windows :: Windows 10
Classifier: Operating System :: POSIX :: Linux
Classifier: Programming Language :: Python :: 3.8
Classifier: Programming Language :: Python :: Implementation :: CPython
Requires-Python: >=3.8.1, <3.9
Requires-Dist: lxml (>=4.5)
Requires-Dist: pymediainfo (>=4.2.1)
Requires-Dist: PySide2 (>=5.14)
Requires-Dist: natsort (>=7.0.1)
